{"_default": {"1": {"star_class": "Ia", "star_type": "O", "star_subtype": 0, "baseMass": 200.0, "baseTemp": 50000, "diameter": 25.0, "star_colour": "Blue"}, "2": {"star_class": "Ia", "star_type": "O", "star_subtype": 1, "baseMass": 176.0, "baseTemp": 48000, "diameter": 24.4, "star_colour": "Blue"}, "3": {"star_class": "Ia", "star_type": "O", "star_subtype": 2, "baseMass": 152.0, "baseTemp": 46000, "diameter": 23.8, "star_colour": "Blue"}, "4": {"star_class": "Ia", "star_type": "O", "star_subtype": 3, "baseMass": 128.0, "baseTemp": 44000, "diameter": 23.2, "star_colour": "Blue"}, "5": {"star_class": "Ia", "star_type": "O", "star_subtype": 4, "baseMass": 104.0, "baseTemp": 42000, "diameter": 22.6, "star_colour": "Blue"}, "6": {"star_class": "Ia", "star_type": "O", "star_subtype": 5, "baseMass": 80.0, "baseTemp": 40000, "diameter": 22.0, "star_colour": "Blue"}, "7": {"star_class": "Ia", "star_type": "O", "star_subtype": 6, "baseMass": 76.0, "baseTemp": 38000, "diameter": 21.6, "star_colour": "Blue"}, "8": {"star_class": "Ia", "star_type": "O", "star_subtype": 7, "baseMass": 72.0, "baseTemp": 36000, "diameter": 21.2, "star_colour": "Blue"}, "9": {"star_class": "Ia", "star_type": "O", "star_subtype": 8, "baseMass": 68.0, "baseTemp": 34000, "diameter": 20.8, "star_colour": "Blue"}, "10": {"star_class": "Ia", "star_type": "O", "star_subtype": 9, "baseMass": 64.0, "baseTemp": 32000, "diameter": 20.4, "star_colour": "Blue"}, "11": {"star_class": "Ia", "star_type": "B", "star_subtype": 0, "baseMass": 60.0, "baseTemp": 30000, "diameter": 20.0, "star_colour": "Blue-White"}, "12": {"star_class": "Ia", "star_type": "B", "star_subtype": 1, "baseMass": 54.0, "baseTemp": 27000, "diameter": 28.0, "star_colour": "Blue-White"}, "13": {"star_class": "Ia", "star_type": "B", "star_subtype": 2, "baseMass": 48.0, "baseTemp": 24000, "diameter": 36.0, "star_colour": "Blue-White"}, "14": {"star_class": "Ia", "star_type": "B", "star_subtype": 3, "baseMass": 42.0, "baseTemp": 21000, "diameter": 44.0, "star_colour": "Blue-White"}, "15": {"star_class": "Ia", "star_type": "B", "star_subtype": 4, "baseMass": 36.0, "baseTemp": 18000, "diameter": 52.0, "star_colour": "Blue-White"}, "16": {"star_class": "Ia", "star_type": "B", "star_subtype": 5, "baseMass": 30.0, "baseTemp": 15000, "diameter": 60.0, "star_colour": "Blue-White"}, "17": {"star_class": "Ia", "star_type": "B", "star_subtype": 6, "baseMass": 28.0, "baseTemp": 14000, "diameter": 72.0, "star_colour": "Blue-White"}, "18": {"star_class": "Ia", "star_type": "B", "star_subtype": 7, "baseMass": 26.0, "baseTemp": 13000, "diameter": 84.0, "star_colour": "Blue-White"}, "19": {"star_class": "Ia", "star_type": "B", "star_subtype": 8, "baseMass": 24.0, "baseTemp": 12000, "diameter": 96.0, "star_colour": "Blue-White"}, "20": {"star_class": "Ia", "star_type": "B", "star_subtype": 9, "baseMass": 22.0, "baseTemp": 10000, "diameter": 108, "star_colour": "Blue-White"}, "21": {"star_class": "Ia", "star_type": "A", "star_subtype": 0, "baseMass": 20.0, "baseTemp": 10000, "diameter": 120, "star_colour": "White"}, "22": {"star_class": "Ia", "star_type": "A", "star_subtype": 1, "baseMass": 19.0, "baseTemp": 9600, "diameter": 132, "star_colour": "White"}, "23": {"star_class": "Ia", "star_type": "A", "star_subtype": 2, "baseMass": 18.0, "baseTemp": 9200, "diameter": 144, "star_colour": "White"}, "24": {"star_class": "Ia", "star_type": "A", "star_subtype": 3, "baseMass": 17.0, "baseTemp": 8800, "diameter": 156, "star_colour": "White"}, "25": {"star_class": "Ia", "star_type": "A", "star_subtype": 4, "baseMass": 16.0, "baseTemp": 8400, "diameter": 168, "star_colour": "White"}, "26": {"star_class": "Ia", "star_type": "A", "star_subtype": 5, "baseMass": 15.0, "baseTemp": 8000, "diameter": 180, "star_colour": "White"}, "27": {"star_class": "Ia", "star_type": "A", "star_subtype": 6, "baseMass": 14.6, "baseTemp": 7600, "diameter": 186, "star_colour": "White"}, "28": {"star_class": "Ia", "star_type": "A", "star_subtype": 7, "baseMass": 14.2, "baseTemp": 7200, "diameter": 192, "star_colour": "White"}, "29": {"star_class": "Ia", "star_type": "A", "star_subtype": 8, "baseMass": 13.8, "baseTemp": 6800, "diameter": 198, "star_colour": "White"}, "30": {"star_class": "Ia", "star_type": "A", "star_subtype": 9, "baseMass": 13.4, "baseTemp": 6400, "diameter": 204, "star_colour": "White"}, "31": {"star_class": "Ia", "star_type": "F", "star_subtype": 0, "baseMass": 13.0, "baseTemp": 7500, "diameter": 210, "star_colour": "Yellow-White"}, "32": {"star_class": "Ia", "star_type": "F", "star_subtype": 1, "baseMass": 12.8, "baseTemp": 7300, "diameter": 224, "star_colour": "Yellow-White"}, "33": {"star_class": "Ia", "star_type": "F", "star_subtype": 2, "baseMass": 12.6, "baseTemp": 7100, "diameter": 238, "star_colour": "Yellow-White"}, "34": {"star_class": "Ia", "star_type": "F", "star_subtype": 3, "baseMass": 12.4, "baseTemp": 6900, "diameter": 252, "star_colour": "Yellow-White"}, "35": {"star_class": "Ia", "star_type": "F", "star_subtype": 4, "baseMass": 12.2, "baseTemp": 6700, "diameter": 266, "star_colour": "Yellow-White"}, "36": {"star_class": "Ia", "star_type": "F", "star_subtype": 5, "baseMass": 12.0, "baseTemp": 6500, "diameter": 280, "star_colour": "Yellow-White"}, "37": {"star_class": "Ia", "star_type": "F", "star_subtype": 6, "baseMass": 12.0, "baseTemp": 6400, "diameter": 290, "star_colour": "Yellow-White"}, "38": {"star_class": "Ia", "star_type": "F", "star_subtype": 7, "baseMass": 12.0, "baseTemp": 6300, "diameter": 300, "star_colour": "Yellow-White"}, "39": {"star_class": "Ia", "star_type": "F", "star_subtype": 8, "baseMass": 12.0, "baseTemp": 6200, "diameter": 310, "star_colour": "Yellow-White"}, "40": {"star_class": "Ia", "star_type": "F", "star_subtype": 9, "baseMass": 12.0, "baseTemp": 6100, "diameter": 320, "star_colour": "Yellow-White"}, "41": {"star_class": "Ia", "star_type": "G", "star_subtype": 0, "baseMass": 12.0, "baseTemp": 6000, "diameter": 330, "star_colour": "Yellow"}, "42": {"star_class": "Ia", "star_type": "G", "star_subtype": 1, "baseMass": 12.2, "baseTemp": 5920, "diameter": 336, "star_colour": "Yellow"}, "43": {"star_class": "Ia", "star_type": "G", "star_subtype": 2, "baseMass": 12.4, "baseTemp": 5840, "diameter": 342, "star_colour": "Yellow"}, "44": {"star_class": "Ia", "star_type": "G", "star_subtype": 3, "baseMass": 12.6, "baseTemp": 5760, "diameter": 348, "star_colour": "Yellow"}, "45": {"star_class": "Ia", "star_type": "G", "star_subtype": 4, "baseMass": 12.8, "baseTemp": 5680, "diameter": 354, "star_colour": "Yellow"}, "46": {"star_class": "Ia", "star_type": "G", "star_subtype": 5, "baseMass": 13.0, "baseTemp": 5600, "diameter": 360, "star_colour": "Yellow"}, "47": {"star_class": "Ia", "star_type": "G", "star_subtype": 6, "baseMass": 13.2, "baseTemp": 5520, "diameter": 372, "star_colour": "Yellow"}, "48": {"star_class": "Ia", "star_type": "G", "star_subtype": 7, "baseMass": 13.4, "baseTemp": 5440, "diameter": 384, "star_colour": "Yellow"}, "49": {"star_class": "Ia", "star_type": "G", "star_subtype": 8, "baseMass": 13.6, "baseTemp": 5360, "diameter": 396, "star_colour": "Yellow"}, "50": {"star_class": "Ia", "star_type": "G", "star_subtype": 9, "baseMass": 13.8, "baseTemp": 5280, "diameter": 408, "star_colour": "Yellow"}, "51": {"star_class": "Ia", "star_type": "K", "star_subtype": 0, "baseMass": 14.0, "baseTemp": 5200, "diameter": 420, "star_colour": "Light Orange"}, "52": {"star_class": "Ia", "star_type": "K", "star_subtype": 1, "baseMass": 14.8, "baseTemp": 5040, "diameter": 458, "star_colour": "Light Orange"}, "53": {"star_class": "Ia", "star_type": "K", "star_subtype": 2, "baseMass": 15.6, "baseTemp": 4880, "diameter": 506, "star_colour": "Light Orange"}, "54": {"star_class": "Ia", "star_type": "K", "star_subtype": 3, "baseMass": 16.4, "baseTemp": 4720, "diameter": 544, "star_colour": "Light Orange"}, "55": {"star_class": "Ia", "star_type": "K", "star_subtype": 4, "baseMass": 17.2, "baseTemp": 4560, "diameter": 582, "star_colour": "Light Orange"}, "56": {"star_class": "Ia", "star_type": "K", "star_subtype": 5, "baseMass": 18.0, "baseTemp": 4400, "diameter": 600, "star_colour": "Light Orange"}, "57": {"star_class": "Ia", "star_type": "K", "star_subtype": 6, "baseMass": 18.4, "baseTemp": 4260, "diameter": 660, "star_colour": "Light Orange"}, "58": {"star_class": "Ia", "star_type": "K", "star_subtype": 7, "baseMass": 18.8, "baseTemp": 4120, "diameter": 720, "star_colour": "Light Orange"}, "59": {"star_class": "Ia", "star_type": "K", "star_subtype": 8, "baseMass": 19.2, "baseTemp": 3920, "diameter": 780, "star_colour": "Light Orange"}, "60": {"star_class": "Ia", "star_type": "K", "star_subtype": 9, "baseMass": 19.6, "baseTemp": 3840, "diameter": 840, "star_colour": "Light Orange"}, "61": {"star_class": "Ia", "star_type": "M", "star_subtype": 0, "baseMass": 20.0, "baseTemp": 3700, "diameter": 60.0, "star_colour": "Orange-Red"}, "62": {"star_class": "Ia", "star_type": "M", "star_subtype": 1, "baseMass": 21.0, "baseTemp": 3560, "diameter": 68.0, "star_colour": "Orange-Red"}, "63": {"star_class": "Ia", "star_type": "M", "star_subtype": 2, "baseMass": 22.0, "baseTemp": 3420, "diameter": 76.0, "star_colour": "Orange-Red"}, "64": {"star_class": "Ia", "star_type": "M", "star_subtype": 3, "baseMass": 23.0, "baseTemp": 3280, "diameter": 84.0, "star_colour": "Orange-Red"}, "65": {"star_class": "Ia", "star_type": "M", "star_subtype": 4, "baseMass": 24.0, "baseTemp": 3140, "diameter": 92.0, "star_colour": "Orange-Red"}, "66": {"star_class": "Ia", "star_type": "M", "star_subtype": 5, "baseMass": 25.0, "baseTemp": 3000, "diameter": 100, "star_colour": "Orange-Red"}, "67": {"star_class": "Ia", "star_type": "M", "star_subtype": 6, "baseMass": 26.2, "baseTemp": 2850, "diameter": 125, "star_colour": "Orange-Red"}, "68": {"star_class": "Ia", "star_type": "M", "star_subtype": 7, "baseMass": 27.5, "baseTemp": 2700, "diameter": 150, "star_colour": "Orange-Red"}, "69": {"star_class": "Ia", "star_type": "M", "star_subtype": 8, "baseMass": 28.8, "baseTemp": 2550, "diameter": 175, "star_colour": "Orange-Red"}, "70": {"star_class": "Ia", "star_type": "M", "star_subtype": 9, "baseMass": 30.0, "baseTemp": 2400, "diameter": 200, "star_colour": "Orange-Red"}, "71": {"star_class": "Ib", "star_type": "O", "star_subtype": 0, "baseMass": 150, "baseTemp": 50000, "diameter": 24.0, "star_colour": "Blue"}, "72": {"star_class": "Ib", "star_type": "O", "star_subtype": 1, "baseMass": 132, "baseTemp": 48000, "diameter": 23.2, "star_colour": "Blue"}, "73": {"star_class": "Ib", "star_type": "O", "star_subtype": 2, "baseMass": 114, "baseTemp": 46000, "diameter": 22.4, "star_colour": "Blue"}, "74": {"star_class": "Ib", "star_type": "O", "star_subtype": 3, "baseMass": 96.0, "baseTemp": 44000, "diameter": 21.6, "star_colour": "Blue"}, "75": {"star_class": "Ib", "star_type": "O", "star_subtype": 4, "baseMass": 78.0, "baseTemp": 42000, "diameter": 20.8, "star_colour": "Blue"}, "76": {"star_class": "Ib", "star_type": "O", "star_subtype": 5, "baseMass": 60.0, "baseTemp": 40000, "diameter": 20.0, "star_colour": "Blue"}, "77": {"star_class": "Ib", "star_type": "O", "star_subtype": 6, "baseMass": 56.0, "baseTemp": 38000, "diameter": 18.8, "star_colour": "Blue"}, "78": {"star_class": "Ib", "star_type": "O", "star_subtype": 7, "baseMass": 52.0, "baseTemp": 36000, "diameter": 17.6, "star_colour": "Blue"}, "79": {"star_class": "Ib", "star_type": "O", "star_subtype": 8, "baseMass": 48.0, "baseTemp": 34000, "diameter": 16.4, "star_colour": "Blue"}, "80": {"star_class": "Ib", "star_type": "O", "star_subtype": 9, "baseMass": 44.0, "baseTemp": 32000, "diameter": 15.2, "star_colour": "Blue"}, "81": {"star_class": "Ib", "star_type": "B", "star_subtype": 0, "baseMass": 40.0, "baseTemp": 30000, "diameter": 14.0, "star_colour": "Blue-White"}, "82": {"star_class": "Ib", "star_type": "B", "star_subtype": 1, "baseMass": 37.0, "baseTemp": 27000, "diameter": 16.2, "star_colour": "Blue-White"}, "83": {"star_class": "Ib", "star_type": "B", "star_subtype": 2, "baseMass": 34.0, "baseTemp": 24000, "diameter": 18.4, "star_colour": "Blue-White"}, "84": {"star_class": "Ib", "star_type": "B", "star_subtype": 3, "baseMass": 31.0, "baseTemp": 21000, "diameter": 20.6, "star_colour": "Blue-White"}, "85": {"star_class": "Ib", "star_type": "B", "star_subtype": 4, "baseMass": 28.0, "baseTemp": 18000, "diameter": 22.8, "star_colour": "Blue-White"}, "86": {"star_class": "Ib", "star_type": "B", "star_subtype": 5, "baseMass": 25.0, "baseTemp": 15000, "diameter": 25.0, "star_colour": "Blue-White"}, "87": {"star_class": "Ib", "star_type": "B", "star_subtype": 6, "baseMass": 23.0, "baseTemp": 14000, "diameter": 30.0, "star_colour": "Blue-White"}, "88": {"star_class": "Ib", "star_type": "B", "star_subtype": 7, "baseMass": 21.0, "baseTemp": 13000, "diameter": 35.0, "star_colour": "Blue-White"}, "89": {"star_class": "Ib", "star_type": "B", "star_subtype": 8, "baseMass": 19.0, "baseTemp": 12000, "diameter": 40.0, "star_colour": "Blue-White"}, "90": {"star_class": "Ib", "star_type": "B", "star_subtype": 9, "baseMass": 17.0, "baseTemp": 10000, "diameter": 45.0, "star_colour": "Blue-White"}, "91": {"star_class": "Ib", "star_type": "A", "star_subtype": 0, "baseMass": 15.0, "baseTemp": 10000, "diameter": 50.0, "star_colour": "White"}, "92": {"star_class": "Ib", "star_type": "A", "star_subtype": 1, "baseMass": 14.6, "baseTemp": 9600, "diameter": 55.0, "star_colour": "White"}, "93": {"star_class": "Ib", "star_type": "A", "star_subtype": 2, "baseMass": 14.2, "baseTemp": 9200, "diameter": 60.0, "star_colour": "White"}, "94": {"star_class": "Ib", "star_type": "A", "star_subtype": 3, "baseMass": 13.8, "baseTemp": 8800, "diameter": 65.0, "star_colour": "White"}, "95": {"star_class": "Ib", "star_type": "A", "star_subtype": 4, "baseMass": 13.4, "baseTemp": 8400, "diameter": 70.0, "star_colour": "White"}, "96": {"star_class": "Ib", "star_type": "A", "star_subtype": 5, "baseMass": 13.0, "baseTemp": 8000, "diameter": 75.0, "star_colour": "White"}, "97": {"star_class": "Ib", "star_type": "A", "star_subtype": 6, "baseMass": 12.8, "baseTemp": 7600, "diameter": 77.0, "star_colour": "White"}, "98": {"star_class": "Ib", "star_type": "A", "star_subtype": 7, "baseMass": 12.6, "baseTemp": 7200, "diameter": 79.0, "star_colour": "White"}, "99": {"star_class": "Ib", "star_type": "A", "star_subtype": 8, "baseMass": 12.4, "baseTemp": 6800, "diameter": 81.0, "star_colour": "White"}, "100": {"star_class": "Ib", "star_type": "A", "star_subtype": 9, "baseMass": 12.2, "baseTemp": 6400, "diameter": 82.0, "star_colour": "White"}, "101": {"star_class": "Ib", "star_type": "F", "star_subtype": 0, "baseMass": 12.0, "baseTemp": 7500, "diameter": 85.0, "star_colour": "Yellow-White"}, "102": {"star_class": "Ib", "star_type": "F", "star_subtype": 1, "baseMass": 11.6, "baseTemp": 7300, "diameter": 91.0, "star_colour": "Yellow-White"}, "103": {"star_class": "Ib", "star_type": "F", "star_subtype": 2, "baseMass": 11.2, "baseTemp": 7100, "diameter": 97.0, "star_colour": "Yellow-White"}, "104": {"star_class": "Ib", "star_type": "F", "star_subtype": 3, "baseMass": 10.8, "baseTemp": 6900, "diameter": 103, "star_colour": "Yellow-White"}, "105": {"star_class": "Ib", "star_type": "F", "star_subtype": 4, "baseMass": 10.4, "baseTemp": 6700, "diameter": 109, "star_colour": "Yellow-White"}, "106": {"star_class": "Ib", "star_type": "F", "star_subtype": 5, "baseMass": 10.0, "baseTemp": 6500, "diameter": 115, "star_colour": "Yellow-White"}, "107": {"star_class": "Ib", "star_type": "F", "star_subtype": 6, "baseMass": 10.0, "baseTemp": 6400, "diameter": 119, "star_colour": "Yellow-White"}, "108": {"star_class": "Ib", "star_type": "F", "star_subtype": 7, "baseMass": 10.0, "baseTemp": 6300, "diameter": 123, "star_colour": "Yellow-White"}, "109": {"star_class": "Ib", "star_type": "F", "star_subtype": 8, "baseMass": 10.0, "baseTemp": 6200, "diameter": 127, "star_colour": "Yellow-White"}, "110": {"star_class": "Ib", "star_type": "F", "star_subtype": 9, "baseMass": 10.0, "baseTemp": 6100, "diameter": 131, "star_colour": "Yellow-White"}, "111": {"star_class": "Ib", "star_type": "G", "star_subtype": 0, "baseMass": 10.0, "baseTemp": 6000, "diameter": 135, "star_colour": "Yellow"}, "112": {"star_class": "Ib", "star_type": "G", "star_subtype": 1, "baseMass": 10.2, "baseTemp": 5920, "diameter": 138, "star_colour": "Yellow"}, "113": {"star_class": "Ib", "star_type": "G", "star_subtype": 2, "baseMass": 10.4, "baseTemp": 5840, "diameter": 144, "star_colour": "Yellow"}, "114": {"star_class": "Ib", "star_type": "G", "star_subtype": 3, "baseMass": 10.6, "baseTemp": 5760, "diameter": 144, "star_colour": "Yellow"}, "115": {"star_class": "Ib", "star_type": "G", "star_subtype": 4, "baseMass": 10.8, "baseTemp": 5680, "diameter": 147, "star_colour": "Yellow"}, "116": {"star_class": "Ib", "star_type": "G", "star_subtype": 5, "baseMass": 11.0, "baseTemp": 5600, "diameter": 150, "star_colour": "Yellow"}, "117": {"star_class": "Ib", "star_type": "G", "star_subtype": 6, "baseMass": 11.2, "baseTemp": 5520, "diameter": 156, "star_colour": "Yellow"}, "118": {"star_class": "Ib", "star_type": "G", "star_subtype": 7, "baseMass": 11.4, "baseTemp": 5440, "diameter": 162, "star_colour": "Yellow"}, "119": {"star_class": "Ib", "star_type": "G", "star_subtype": 8, "baseMass": 11.6, "baseTemp": 5360, "diameter": 168, "star_colour": "Yellow"}, "120": {"star_class": "Ib", "star_type": "G", "star_subtype": 9, "baseMass": 11.8, "baseTemp": 5280, "diameter": 174, "star_colour": "Yellow"}, "121": {"star_class": "Ib", "star_type": "K", "star_subtype": 0, "baseMass": 12.0, "baseTemp": 5200, "diameter": 180, "star_colour": "Light Orange"}, "122": {"star_class": "Ib", "star_type": "K", "star_subtype": 1, "baseMass": 12.2, "baseTemp": 5040, "diameter": 196, "star_colour": "Light Orange"}, "123": {"star_class": "Ib", "star_type": "K", "star_subtype": 2, "baseMass": 12.4, "baseTemp": 4880, "diameter": 212, "star_colour": "Light Orange"}, "124": {"star_class": "Ib", "star_type": "K", "star_subtype": 3, "baseMass": 12.6, "baseTemp": 4720, "diameter": 228, "star_colour": "Light Orange"}, "125": {"star_class": "Ib", "star_type": "K", "star_subtype": 4, "baseMass": 12.8, "baseTemp": 4560, "diameter": 244, "star_colour": "Light Orange"}, "126": {"star_class": "Ib", "star_type": "K", "star_subtype": 5, "baseMass": 13.0, "baseTemp": 4400, "diameter": 260, "star_colour": "Light Orange"}, "127": {"star_class": "Ib", "star_type": "K", "star_subtype": 6, "baseMass": 13.4, "baseTemp": 4260, "diameter": 284, "star_colour": "Light Orange"}, "128": {"star_class": "Ib", "star_type": "K", "star_subtype": 7, "baseMass": 13.8, "baseTemp": 4120, "diameter": 308, "star_colour": "Light Orange"}, "129": {"star_class": "Ib", "star_type": "K", "star_subtype": 8, "baseMass": 14.2, "baseTemp": 3920, "diameter": 332, "star_colour": "Light Orange"}, "130": {"star_class": "Ib", "star_type": "K", "star_subtype": 9, "baseMass": 14.6, "baseTemp": 3840, "diameter": 356, "star_colour": "Light Orange"}, "131": {"star_class": "Ib", "star_type": "M", "star_subtype": 0, "baseMass": 15.0, "baseTemp": 3700, "diameter": 380, "star_colour": "Orange-Red"}, "132": {"star_class": "Ib", "star_type": "M", "star_subtype": 1, "baseMass": 16.0, "baseTemp": 3560, "diameter": 424, "star_colour": "Orange-Red"}, "133": {"star_class": "Ib", "star_type": "M", "star_subtype": 2, "baseMass": 17.0, "baseTemp": 3420, "diameter": 468, "star_colour": "Orange-Red"}, "134": {"star_class": "Ib", "star_type": "M", "star_subtype": 3, "baseMass": 18.0, "baseTemp": 3280, "diameter": 512, "star_colour": "Orange-Red"}, "135": {"star_class": "Ib", "star_type": "M", "star_subtype": 4, "baseMass": 19.0, "baseTemp": 3140, "diameter": 556, "star_colour": "Orange-Red"}, "136": {"star_class": "Ib", "star_type": "M", "star_subtype": 5, "baseMass": 20.0, "baseTemp": 3000, "diameter": 600, "star_colour": "Orange-Red"}, "137": {"star_class": "Ib", "star_type": "M", "star_subtype": 6, "baseMass": 21.2, "baseTemp": 2850, "diameter": 650, "star_colour": "Orange-Red"}, "138": {"star_class": "Ib", "star_type": "M", "star_subtype": 7, "baseMass": 23.5, "baseTemp": 2700, "diameter": 700, "star_colour": "Orange-Red"}, "139": {"star_class": "Ib", "star_type": "M", "star_subtype": 8, "baseMass": 23.8, "baseTemp": 2550, "diameter": 750, "star_colour": "Orange-Red"}, "140": {"star_class": "Ib", "star_type": "M", "star_subtype": 9, "baseMass": 25.0, "baseTemp": 2400, "diameter": 800, "star_colour": "Orange-Red"}, "141": {"star_class": "II", "star_type": "O", "star_subtype": 0, "baseMass": 130, "baseTemp": 50000, "diameter": 22.0, "star_colour": "Blue"}, "142": {"star_class": "II", "star_type": "O", "star_subtype": 1, "baseMass": 112, "baseTemp": 48000, "diameter": 21.2, "star_colour": "Blue"}, "143": {"star_class": "II", "star_type": "O", "star_subtype": 2, "baseMass": 94.0, "baseTemp": 46000, "diameter": 20.4, "star_colour": "Blue"}, "144": {"star_class": "II", "star_type": "O", "star_subtype": 3, "baseMass": 76.0, "baseTemp": 44000, "diameter": 19.6, "star_colour": "Blue"}, "145": {"star_class": "II", "star_type": "O", "star_subtype": 4, "baseMass": 58.0, "baseTemp": 42000, "diameter": 18.8, "star_colour": "Blue"}, "146": {"star_class": "II", "star_type": "O", "star_subtype": 5, "baseMass": 40.0, "baseTemp": 40000, "diameter": 18.0, "star_colour": "Blue"}, "147": {"star_class": "II", "star_type": "O", "star_subtype": 6, "baseMass": 38.0, "baseTemp": 38000, "diameter": 16.8, "star_colour": "Blue"}, "148": {"star_class": "II", "star_type": "O", "star_subtype": 7, "baseMass": 36.0, "baseTemp": 36000, "diameter": 15.6, "star_colour": "Blue"}, "149": {"star_class": "II", "star_type": "O", "star_subtype": 8, "baseMass": 34.0, "baseTemp": 34000, "diameter": 14.4, "star_colour": "Blue"}, "150": {"star_class": "II", "star_type": "O", "star_subtype": 9, "baseMass": 32.0, "baseTemp": 32000, "diameter": 13.2, "star_colour": "Blue"}, "151": {"star_class": "II", "star_type": "B", "star_subtype": 0, "baseMass": 30.0, "baseTemp": 30000, "diameter": 12.0, "star_colour": "Blue-White"}, "152": {"star_class": "II", "star_type": "B", "star_subtype": 1, "baseMass": 28.0, "baseTemp": 27000, "diameter": 12.4, "star_colour": "Blue-White"}, "153": {"star_class": "II", "star_type": "B", "star_subtype": 2, "baseMass": 26.0, "baseTemp": 24000, "diameter": 12.8, "star_colour": "Blue-White"}, "154": {"star_class": "II", "star_type": "B", "star_subtype": 3, "baseMass": 24.0, "baseTemp": 21000, "diameter": 13.2, "star_colour": "Blue-White"}, "155": {"star_class": "II", "star_type": "B", "star_subtype": 4, "baseMass": 22.0, "baseTemp": 18000, "diameter": 13.6, "star_colour": "Blue-White"}, "156": {"star_class": "II", "star_type": "B", "star_subtype": 5, "baseMass": 20.0, "baseTemp": 15000, "diameter": 14.0, "star_colour": "Blue-White"}, "157": {"star_class": "II", "star_type": "B", "star_subtype": 6, "baseMass": 18.8, "baseTemp": 14000, "diameter": 17.2, "star_colour": "Blue-White"}, "158": {"star_class": "II", "star_type": "B", "star_subtype": 7, "baseMass": 17.6, "baseTemp": 13000, "diameter": 20.4, "star_colour": "Blue-White"}, "159": {"star_class": "II", "star_type": "B", "star_subtype": 8, "baseMass": 16.4, "baseTemp": 12000, "diameter": 23.6, "star_colour": "Blue-White"}, "160": {"star_class": "II", "star_type": "B", "star_subtype": 9, "baseMass": 15.2, "baseTemp": 10000, "diameter": 26.8, "star_colour": "Blue-White"}, "161": {"star_class": "II", "star_type": "A", "star_subtype": 0, "baseMass": 14.0, "baseTemp": 10000, "diameter": 30.0, "star_colour": "White"}, "162": {"star_class": "II", "star_type": "A", "star_subtype": 1, "baseMass": 13.4, "baseTemp": 9600, "diameter": 33.0, "star_colour": "White"}, "163": {"star_class": "II", "star_type": "A", "star_subtype": 2, "baseMass": 12.8, "baseTemp": 9200, "diameter": 36.0, "star_colour": "White"}, "164": {"star_class": "II", "star_type": "A", "star_subtype": 3, "baseMass": 12.2, "baseTemp": 8800, "diameter": 39.0, "star_colour": "White"}, "165": {"star_class": "II", "star_type": "A", "star_subtype": 4, "baseMass": 11.6, "baseTemp": 8400, "diameter": 42.0, "star_colour": "White"}, "166": {"star_class": "II", "star_type": "A", "star_subtype": 5, "baseMass": 11.0, "baseTemp": 8000, "diameter": 45.0, "star_colour": "White"}, "167": {"star_class": "II", "star_type": "A", "star_subtype": 6, "baseMass": 10.8, "baseTemp": 7600, "diameter": 46.0, "star_colour": "White"}, "168": {"star_class": "II", "star_type": "A", "star_subtype": 7, "baseMass": 10.6, "baseTemp": 7200, "diameter": 47.0, "star_colour": "White"}, "169": {"star_class": "II", "star_type": "A", "star_subtype": 8, "baseMass": 10.4, "baseTemp": 6800, "diameter": 48.0, "star_colour": "White"}, "170": {"star_class": "II", "star_type": "A", "star_subtype": 9, "baseMass": 10.2, "baseTemp": 6400, "diameter": 49.0, "star_colour": "White"}, "171": {"star_class": "II", "star_type": "F", "star_subtype": 0, "baseMass": 10.0, "baseTemp": 7500, "diameter": 50.0, "star_colour": "Yellow-White"}, "172": {"star_class": "II", "star_type": "F", "star_subtype": 1, "baseMass": 9.6, "baseTemp": 7300, "diameter": 53.2, "star_colour": "Yellow-White"}, "173": {"star_class": "II", "star_type": "F", "star_subtype": 2, "baseMass": 9.2, "baseTemp": 7100, "diameter": 56.4, "star_colour": "Yellow-White"}, "174": {"star_class": "II", "star_type": "F", "star_subtype": 3, "baseMass": 8.8, "baseTemp": 6900, "diameter": 59.6, "star_colour": "Yellow-White"}, "175": {"star_class": "II", "star_type": "F", "star_subtype": 4, "baseMass": 8.4, "baseTemp": 6700, "diameter": 62.8, "star_colour": "Yellow-White"}, "176": {"star_class": "II", "star_type": "F", "star_subtype": 5, "baseMass": 8.0, "baseTemp": 6500, "diameter": 66.0, "star_colour": "Yellow-White"}, "177": {"star_class": "II", "star_type": "F", "star_subtype": 6, "baseMass": 8.0, "baseTemp": 6400, "diameter": 68.2, "star_colour": "Yellow-White"}, "178": {"star_class": "II", "star_type": "F", "star_subtype": 7, "baseMass": 8.0, "baseTemp": 6300, "diameter": 70.4, "star_colour": "Yellow-White"}, "179": {"star_class": "II", "star_type": "F", "star_subtype": 8, "baseMass": 8.0, "baseTemp": 6200, "diameter": 72.6, "star_colour": "Yellow-White"}, "180": {"star_class": "II", "star_type": "F", "star_subtype": 9, "baseMass": 8.0, "baseTemp": 6100, "diameter": 74.8, "star_colour": "Yellow-White"}, "181": {"star_class": "II", "star_type": "G", "star_subtype": 0, "baseMass": 8.0, "baseTemp": 6000, "diameter": 77.0, "star_colour": "Yellow"}, "182": {"star_class": "II", "star_type": "G", "star_subtype": 1, "baseMass": 8.4, "baseTemp": 5920, "diameter": 79.6, "star_colour": "Yellow"}, "183": {"star_class": "II", "star_type": "G", "star_subtype": 2, "baseMass": 8.8, "baseTemp": 5840, "diameter": 82.2, "star_colour": "Yellow"}, "184": {"star_class": "II", "star_type": "G", "star_subtype": 3, "baseMass": 9.2, "baseTemp": 5760, "diameter": 84.8, "star_colour": "Yellow"}, "185": {"star_class": "II", "star_type": "G", "star_subtype": 4, "baseMass": 9.6, "baseTemp": 5680, "diameter": 87.4, "star_colour": "Yellow"}, "186": {"star_class": "II", "star_type": "G", "star_subtype": 5, "baseMass": 10.0, "baseTemp": 5600, "diameter": 90.0, "star_colour": "Yellow"}, "187": {"star_class": "II", "star_type": "G", "star_subtype": 6, "baseMass": 10.0, "baseTemp": 5520, "diameter": 94.0, "star_colour": "Yellow"}, "188": {"star_class": "II", "star_type": "G", "star_subtype": 7, "baseMass": 10.0, "baseTemp": 5440, "diameter": 98.0, "star_colour": "Yellow"}, "189": {"star_class": "II", "star_type": "G", "star_subtype": 8, "baseMass": 10.0, "baseTemp": 5360, "diameter": 102, "star_colour": "Yellow"}, "190": {"star_class": "II", "star_type": "G", "star_subtype": 9, "baseMass": 10.0, "baseTemp": 5280, "diameter": 106, "star_colour": "Yellow"}, "191": {"star_class": "II", "star_type": "K", "star_subtype": 0, "baseMass": 10.0, "baseTemp": 5200, "diameter": 110, "star_colour": "Light Orange"}, "192": {"star_class": "II", "star_type": "K", "star_subtype": 1, "baseMass": 10.4, "baseTemp": 5040, "diameter": 120, "star_colour": "Light Orange"}, "193": {"star_class": "II", "star_type": "K", "star_subtype": 2, "baseMass": 10.8, "baseTemp": 4880, "diameter": 130, "star_colour": "Light Orange"}, "194": {"star_class": "II", "star_type": "K", "star_subtype": 3, "baseMass": 11.2, "baseTemp": 4720, "diameter": 140, "star_colour": "Light Orange"}, "195": {"star_class": "II", "star_type": "K", "star_subtype": 4, "baseMass": 11.6, "baseTemp": 4560, "diameter": 150, "star_colour": "Light Orange"}, "196": {"star_class": "II", "star_type": "K", "star_subtype": 5, "baseMass": 12.0, "baseTemp": 4400, "diameter": 160, "star_colour": "Light Orange"}, "197": {"star_class": "II", "star_type": "K", "star_subtype": 6, "baseMass": 12.4, "baseTemp": 4260, "diameter": 174, "star_colour": "Light Orange"}, "198": {"star_class": "II", "star_type": "K", "star_subtype": 7, "baseMass": 12.8, "baseTemp": 4120, "diameter": 188, "star_colour": "Light Orange"}, "199": {"star_class": "II", "star_type": "K", "star_subtype": 8, "baseMass": 13.2, "baseTemp": 3920, "diameter": 202, "star_colour": "Light Orange"}, "200": {"star_class": "II", "star_type": "K", "star_subtype": 9, "baseMass": 13.6, "baseTemp": 3840, "diameter": 216, "star_colour": "Light Orange"}, "201": {"star_class": "II", "star_type": "M", "star_subtype": 0, "baseMass": 14.0, "baseTemp": 3700, "diameter": 230, "star_colour": "Orange-Red"}, "202": {"star_class": "II", "star_type": "M", "star_subtype": 1, "baseMass": 14.4, "baseTemp": 3560, "diameter": 254, "star_colour": "Orange-Red"}, "203": {"star_class": "II", "star_type": "M", "star_subtype": 2, "baseMass": 14.8, "baseTemp": 3420, "diameter": 278, "star_colour": "Orange-Red"}, "204": {"star_class": "II", "star_type": "M", "star_subtype": 3, "baseMass": 15.2, "baseTemp": 3280, "diameter": 302, "star_colour": "Orange-Red"}, "205": {"star_class": "II", "star_type": "M", "star_subtype": 4, "baseMass": 15.6, "baseTemp": 3140, "diameter": 326, "star_colour": "Orange-Red"}, "206": {"star_class": "II", "star_type": "M", "star_subtype": 5, "baseMass": 16.0, "baseTemp": 3000, "diameter": 350, "star_colour": "Orange-Red"}, "207": {"star_class": "II", "star_type": "M", "star_subtype": 6, "baseMass": 16.5, "baseTemp": 2850, "diameter": 387, "star_colour": "Orange-Red"}, "208": {"star_class": "II", "star_type": "M", "star_subtype": 7, "baseMass": 17.0, "baseTemp": 2700, "diameter": 425, "star_colour": "Orange-Red"}, "209": {"star_class": "II", "star_type": "M", "star_subtype": 8, "baseMass": 17.5, "baseTemp": 2550, "diameter": 463, "star_colour": "Orange-Red"}, "210": {"star_class": "II", "star_type": "M", "star_subtype": 9, "baseMass": 18.0, "baseTemp": 2400, "diameter": 500, "star_colour": "Orange-Red"}, "211": {"star_class": "III", "star_type": "O", "star_subtype": 0, "baseMass": 110.0, "baseTemp": 50000, "diameter": 21.0, "star_colour": "Blue"}, "212": {"star_class": "III", "star_type": "O", "star_subtype": 1, "baseMass": 94.0, "baseTemp": 48000, "diameter": 19.8, "star_colour": "Blue"}, "213": {"star_class": "III", "star_type": "O", "star_subtype": 2, "baseMass": 78.0, "baseTemp": 46000, "diameter": 18.6, "star_colour": "Blue"}, "214": {"star_class": "III", "star_type": "O", "star_subtype": 3, "baseMass": 62.0, "baseTemp": 44000, "diameter": 17.4, "star_colour": "Blue"}, "215": {"star_class": "III", "star_type": "O", "star_subtype": 4, "baseMass": 46.0, "baseTemp": 42000, "diameter": 16.2, "star_colour": "Blue"}, "216": {"star_class": "III", "star_type": "O", "star_subtype": 5, "baseMass": 30.0, "baseTemp": 40000, "diameter": 15.0, "star_colour": "Blue"}, "217": {"star_class": "III", "star_type": "O", "star_subtype": 6, "baseMass": 28.0, "baseTemp": 38000, "diameter": 14.0, "star_colour": "Blue"}, "218": {"star_class": "III", "star_type": "O", "star_subtype": 7, "baseMass": 26.0, "baseTemp": 36000, "diameter": 13.0, "star_colour": "Blue"}, "219": {"star_class": "III", "star_type": "O", "star_subtype": 8, "baseMass": 24.0, "baseTemp": 34000, "diameter": 12.0, "star_colour": "Blue"}, "220": {"star_class": "III", "star_type": "O", "star_subtype": 9, "baseMass": 22.0, "baseTemp": 32000, "diameter": 11.0, "star_colour": "Blue"}, "221": {"star_class": "III", "star_type": "B", "star_subtype": 0, "baseMass": 20.0, "baseTemp": 30000, "diameter": 10.0, "star_colour": "Blue-White"}, "222": {"star_class": "III", "star_type": "B", "star_subtype": 1, "baseMass": 18.0, "baseTemp": 27000, "diameter": 9.2, "star_colour": "Blue-White"}, "223": {"star_class": "III", "star_type": "B", "star_subtype": 2, "baseMass": 16.0, "baseTemp": 24000, "diameter": 8.4, "star_colour": "Blue-White"}, "224": {"star_class": "III", "star_type": "B", "star_subtype": 3, "baseMass": 14.0, "baseTemp": 21000, "diameter": 7.6, "star_colour": "Blue-White"}, "225": {"star_class": "III", "star_type": "B", "star_subtype": 4, "baseMass": 12.0, "baseTemp": 18000, "diameter": 6.8, "star_colour": "Blue-White"}, "226": {"star_class": "III", "star_type": "B", "star_subtype": 5, "baseMass": 10.0, "baseTemp": 15000, "diameter": 6.0, "star_colour": "Blue-White"}, "227": {"star_class": "III", "star_type": "B", "star_subtype": 6, "baseMass": 9.6, "baseTemp": 14000, "diameter": 5.8, "star_colour": "Blue-White"}, "228": {"star_class": "III", "star_type": "B", "star_subtype": 7, "baseMass": 9.2, "baseTemp": 13000, "diameter": 5.6, "star_colour": "Blue-White"}, "229": {"star_class": "III", "star_type": "B", "star_subtype": 8, "baseMass": 8.8, "baseTemp": 12000, "diameter": 5.4, "star_colour": "Blue-White"}, "230": {"star_class": "III", "star_type": "B", "star_subtype": 9, "baseMass": 8.4, "baseTemp": 10000, "diameter": 5.2, "star_colour": "Blue-White"}, "231": {"star_class": "III", "star_type": "A", "star_subtype": 0, "baseMass": 8.0, "baseTemp": 10000, "diameter": 5.0, "star_colour": "White"}, "232": {"star_class": "III", "star_type": "A", "star_subtype": 1, "baseMass": 7.6, "baseTemp": 9600, "diameter": 5.0, "star_colour": "White"}, "233": {"star_class": "III", "star_type": "A", "star_subtype": 2, "baseMass": 7.2, "baseTemp": 9200, "diameter": 5.0, "star_colour": "White"}, "234": {"star_class": "III", "star_type": "A", "star_subtype": 3, "baseMass": 6.8, "baseTemp": 8800, "diameter": 5.0, "star_colour": "White"}, "235": {"star_class": "III", "star_type": "A", "star_subtype": 4, "baseMass": 6.4, "baseTemp": 8400, "diameter": 5.0, "star_colour": "White"}, "236": {"star_class": "III", "star_type": "A", "star_subtype": 5, "baseMass": 6.0, "baseTemp": 8000, "diameter": 5.0, "star_colour": "White"}, "237": {"star_class": "III", "star_type": "A", "star_subtype": 6, "baseMass": 5.6, "baseTemp": 7600, "diameter": 5.0, "star_colour": "White"}, "238": {"star_class": "III", "star_type": "A", "star_subtype": 7, "baseMass": 5.2, "baseTemp": 7200, "diameter": 5.0, "star_colour": "White"}, "239": {"star_class": "III", "star_type": "A", "star_subtype": 8, "baseMass": 4.8, "baseTemp": 6800, "diameter": 5.0, "star_colour": "White"}, "240": {"star_class": "III", "star_type": "A", "star_subtype": 9, "baseMass": 4.4, "baseTemp": 6400, "diameter": 5.0, "star_colour": "White"}, "241": {"star_class": "III", "star_type": "F", "star_subtype": 0, "baseMass": 4.0, "baseTemp": 7500, "diameter": 1.7, "star_colour": "Yellow-White"}, "242": {"star_class": "III", "star_type": "F", "star_subtype": 1, "baseMass": 3.8, "baseTemp": 7300, "diameter": 1.66, "star_colour": "Yellow-White"}, "243": {"star_class": "III", "star_type": "F", "star_subtype": 2, "baseMass": 3.6, "baseTemp": 7100, "diameter": 1.62, "star_colour": "Yellow-White"}, "244": {"star_class": "III", "star_type": "F", "star_subtype": 3, "baseMass": 3.4, "baseTemp": 6900, "diameter": 1.58, "star_colour": "Yellow-White"}, "245": {"star_class": "III", "star_type": "F", "star_subtype": 4, "baseMass": 3.2, "baseTemp": 6700, "diameter": 1.54, "star_colour": "Yellow-White"}, "246": {"star_class": "III", "star_type": "F", "star_subtype": 5, "baseMass": 3.0, "baseTemp": 6500, "diameter": 1.5, "star_colour": "Yellow-White"}, "247": {"star_class": "III", "star_type": "F", "star_subtype": 6, "baseMass": 2.9, "baseTemp": 6400, "diameter": 1.42, "star_colour": "Yellow-White"}, "248": {"star_class": "III", "star_type": "F", "star_subtype": 7, "baseMass": 2.8, "baseTemp": 6300, "diameter": 1.34, "star_colour": "Yellow-White"}, "249": {"star_class": "III", "star_type": "F", "star_subtype": 8, "baseMass": 2.7, "baseTemp": 6200, "diameter": 1.26, "star_colour": "Yellow-White"}, "250": {"star_class": "III", "star_type": "F", "star_subtype": 9, "baseMass": 2.6, "baseTemp": 6100, "diameter": 1.18, "star_colour": "Yellow-White"}, "251": {"star_class": "III", "star_type": "G", "star_subtype": 0, "baseMass": 2.5, "baseTemp": 6000, "diameter": 10.0, "star_colour": "Yellow"}, "252": {"star_class": "III", "star_type": "G", "star_subtype": 1, "baseMass": 2.4, "baseTemp": 5920, "diameter": 11.0, "star_colour": "Yellow"}, "253": {"star_class": "III", "star_type": "G", "star_subtype": 2, "baseMass": 2.3, "baseTemp": 5840, "diameter": 12.0, "star_colour": "Yellow"}, "254": {"star_class": "III", "star_type": "G", "star_subtype": 3, "baseMass": 2.2, "baseTemp": 5760, "diameter": 13.0, "star_colour": "Yellow"}, "255": {"star_class": "III", "star_type": "G", "star_subtype": 4, "baseMass": 2.1, "baseTemp": 5680, "diameter": 14.0, "star_colour": "Yellow"}, "256": {"star_class": "III", "star_type": "G", "star_subtype": 5, "baseMass": 2.0, "baseTemp": 5600, "diameter": 15.0, "star_colour": "Yellow"}, "257": {"star_class": "III", "star_type": "G", "star_subtype": 6, "baseMass": 1.82, "baseTemp": 5520, "diameter": 16.0, "star_colour": "Yellow"}, "258": {"star_class": "III", "star_type": "G", "star_subtype": 7, "baseMass": 1.64, "baseTemp": 5440, "diameter": 17.0, "star_colour": "Yellow"}, "259": {"star_class": "III", "star_type": "G", "star_subtype": 8, "baseMass": 1.46, "baseTemp": 5360, "diameter": 18.0, "star_colour": "Yellow"}, "260": {"star_class": "III", "star_type": "G", "star_subtype": 9, "baseMass": 1.28, "baseTemp": 5280, "diameter": 19.0, "star_colour": "Yellow"}, "261": {"star_class": "III", "star_type": "K", "star_subtype": 0, "baseMass": 1.1, "baseTemp": 5200, "diameter": 20.0, "star_colour": "Light Orange"}, "262": {"star_class": "III", "star_type": "K", "star_subtype": 1, "baseMass": 1.18, "baseTemp": 5040, "diameter": 24.0, "star_colour": "Light Orange"}, "263": {"star_class": "III", "star_type": "K", "star_subtype": 2, "baseMass": 1.26, "baseTemp": 4880, "diameter": 28.0, "star_colour": "Light Orange"}, "264": {"star_class": "III", "star_type": "K", "star_subtype": 3, "baseMass": 1.34, "baseTemp": 4720, "diameter": 32.0, "star_colour": "Light Orange"}, "265": {"star_class": "III", "star_type": "K", "star_subtype": 4, "baseMass": 1.42, "baseTemp": 4560, "diameter": 36.0, "star_colour": "Light Orange"}, "266": {"star_class": "III", "star_type": "K", "star_subtype": 5, "baseMass": 1.5, "baseTemp": 4400, "diameter": 40.0, "star_colour": "Light Orange"}, "267": {"star_class": "III", "star_type": "K", "star_subtype": 6, "baseMass": 1.56, "baseTemp": 4260, "diameter": 44.0, "star_colour": "Light Orange"}, "268": {"star_class": "III", "star_type": "K", "star_subtype": 7, "baseMass": 1.62, "baseTemp": 4120, "diameter": 48.0, "star_colour": "Light Orange"}, "269": {"star_class": "III", "star_type": "K", "star_subtype": 8, "baseMass": 1.68, "baseTemp": 3920, "diameter": 52.0, "star_colour": "Light Orange"}, "270": {"star_class": "III", "star_type": "K", "star_subtype": 9, "baseMass": 1.74, "baseTemp": 3840, "diameter": 56.0, "star_colour": "Light Orange"}, "271": {"star_class": "III", "star_type": "M", "star_subtype": 0, "baseMass": 1.8, "baseTemp": 3700, "diameter": 60.0, "star_colour": "Orange-Red"}, "272": {"star_class": "III", "star_type": "M", "star_subtype": 1, "baseMass": 1.92, "baseTemp": 3560, "diameter": 68.0, "star_colour": "Orange-Red"}, "273": {"star_class": "III", "star_type": "M", "star_subtype": 2, "baseMass": 2.04, "baseTemp": 3420, "diameter": 76.0, "star_colour": "Orange-Red"}, "274": {"star_class": "III", "star_type": "M", "star_subtype": 3, "baseMass": 2.16, "baseTemp": 3280, "diameter": 84.0, "star_colour": "Orange-Red"}, "275": {"star_class": "III", "star_type": "M", "star_subtype": 4, "baseMass": 2.28, "baseTemp": 3140, "diameter": 92.0, "star_colour": "Orange-Red"}, "276": {"star_class": "III", "star_type": "M", "star_subtype": 5, "baseMass": 2.4, "baseTemp": 3000, "diameter": 100, "star_colour": "Orange-Red"}, "277": {"star_class": "III", "star_type": "M", "star_subtype": 6, "baseMass": 3.8, "baseTemp": 2850, "diameter": 125, "star_colour": "Orange-Red"}, "278": {"star_class": "III", "star_type": "M", "star_subtype": 7, "baseMass": 5.2, "baseTemp": 2700, "diameter": 150, "star_colour": "Orange-Red"}, "279": {"star_class": "III", "star_type": "M", "star_subtype": 8, "baseMass": 6.6, "baseTemp": 2550, "diameter": 175, "star_colour": "Orange-Red"}, "280": {"star_class": "III", "star_type": "M", "star_subtype": 9, "baseMass": 8.0, "baseTemp": 2400, "diameter": 200, "star_colour": "Orange-Red"}, "281": {"star_class": "IV", "star_type": "B", "star_subtype": 0, "baseMass": 20.0, "baseTemp": 30000, "diameter": 8.0, "star_colour": "Blue-White"}, "282": {"star_class": "IV", "star_type": "B", "star_subtype": 1, "baseMass": 18.0, "baseTemp": 27000, "diameter": 7.4, "star_colour": "Blue-White"}, "283": {"star_class": "IV", "star_type": "B", "star_subtype": 2, "baseMass": 16.0, "baseTemp": 24000, "diameter": 6.8, "star_colour": "Blue-White"}, "284": {"star_class": "IV", "star_type": "B", "star_subtype": 3, "baseMass": 14.0, "baseTemp": 21000, "diameter": 6.2, "star_colour": "Blue-White"}, "285": {"star_class": "IV", "star_type": "B", "star_subtype": 4, "baseMass": 12.0, "baseTemp": 18000, "diameter": 5.6, "star_colour": "Blue-White"}, "286": {"star_class": "IV", "star_type": "B", "star_subtype": 5, "baseMass": 10.0, "baseTemp": 15000, "diameter": 8.0, "star_colour": "Blue-White"}, "287": {"star_class": "IV", "star_type": "B", "star_subtype": 6, "baseMass": 8.8, "baseTemp": 14000, "diameter": 4.8, "star_colour": "Blue-White"}, "288": {"star_class": "IV", "star_type": "B", "star_subtype": 7, "baseMass": 7.6, "baseTemp": 13000, "diameter": 4.6, "star_colour": "Blue-White"}, "289": {"star_class": "IV", "star_type": "B", "star_subtype": 8, "baseMass": 6.4, "baseTemp": 12000, "diameter": 4.4, "star_colour": "Blue-White"}, "290": {"star_class": "IV", "star_type": "B", "star_subtype": 9, "baseMass": 5.2, "baseTemp": 11000, "diameter": 4.2, "star_colour": "Blue-White"}, "291": {"star_class": "IV", "star_type": "A", "star_subtype": 0, "baseMass": 4.0, "baseTemp": 10000, "diameter": 4.0, "star_colour": "White"}, "292": {"star_class": "IV", "star_type": "A", "star_subtype": 1, "baseMass": 3.66, "baseTemp": 9600, "diameter": 3.8, "star_colour": "White"}, "293": {"star_class": "IV", "star_type": "A", "star_subtype": 2, "baseMass": 3.32, "baseTemp": 9200, "diameter": 3.6, "star_colour": "White"}, "294": {"star_class": "IV", "star_type": "A", "star_subtype": 3, "baseMass": 2.98, "baseTemp": 8800, "diameter": 3.4, "star_colour": "White"}, "295": {"star_class": "IV", "star_type": "A", "star_subtype": 4, "baseMass": 2.64, "baseTemp": 8400, "diameter": 3.2, "star_colour": "White"}, "296": {"star_class": "IV", "star_type": "A", "star_subtype": 5, "baseMass": 2.3, "baseTemp": 8000, "diameter": 3.0, "star_colour": "White"}, "297": {"star_class": "IV", "star_type": "A", "star_subtype": 6, "baseMass": 2.24, "baseTemp": 7900, "diameter": 2.9, "star_colour": "White"}, "298": {"star_class": "IV", "star_type": "A", "star_subtype": 7, "baseMass": 2.18, "baseTemp": 7800, "diameter": 2.8, "star_colour": "White"}, "299": {"star_class": "IV", "star_type": "A", "star_subtype": 8, "baseMass": 2.12, "baseTemp": 7700, "diameter": 2.8, "star_colour": "White"}, "300": {"star_class": "IV", "star_type": "A", "star_subtype": 9, "baseMass": 2.06, "baseTemp": 7600, "diameter": 2.9, "star_colour": "White"}, "301": {"star_class": "IV", "star_type": "F", "star_subtype": 0, "baseMass": 2.0, "baseTemp": 7500, "diameter": 4.0, "star_colour": "Yellow-White"}, "302": {"star_class": "IV", "star_type": "F", "star_subtype": 1, "baseMass": 1.9, "baseTemp": 7300, "diameter": 3.8, "star_colour": "Yellow-White"}, "303": {"star_class": "IV", "star_type": "F", "star_subtype": 2, "baseMass": 1.8, "baseTemp": 7100, "diameter": 3.6, "star_colour": "Yellow-White"}, "304": {"star_class": "IV", "star_type": "F", "star_subtype": 3, "baseMass": 1.7, "baseTemp": 6900, "diameter": 3.4, "star_colour": "Yellow-White"}, "305": {"star_class": "IV", "star_type": "F", "star_subtype": 4, "baseMass": 1.6, "baseTemp": 6700, "diameter": 3.2, "star_colour": "Yellow-White"}, "306": {"star_class": "IV", "star_type": "F", "star_subtype": 5, "baseMass": 1.5, "baseTemp": 6500, "diameter": 3.0, "star_colour": "Yellow-White"}, "307": {"star_class": "IV", "star_type": "F", "star_subtype": 6, "baseMass": 1.4, "baseTemp": 6400, "diameter": 3.0, "star_colour": "Yellow-White"}, "308": {"star_class": "IV", "star_type": "F", "star_subtype": 7, "baseMass": 1.4, "baseTemp": 6300, "diameter": 3.0, "star_colour": "Yellow-White"}, "309": {"star_class": "IV", "star_type": "F", "star_subtype": 8, "baseMass": 1.5, "baseTemp": 6200, "diameter": 3.0, "star_colour": "Yellow-White"}, "310": {"star_class": "IV", "star_type": "F", "star_subtype": 9, "baseMass": 1.6, "baseTemp": 6100, "diameter": 3.0, "star_colour": "Yellow-White"}, "311": {"star_class": "IV", "star_type": "G", "star_subtype": 0, "baseMass": 1.7, "baseTemp": 6000, "diameter": 3.0, "star_colour": "Yellow"}, "312": {"star_class": "IV", "star_type": "G", "star_subtype": 1, "baseMass": 1.52, "baseTemp": 5920, "diameter": 3.2, "star_colour": "Yellow"}, "313": {"star_class": "IV", "star_type": "G", "star_subtype": 2, "baseMass": 1.44, "baseTemp": 5840, "diameter": 3.4, "star_colour": "Yellow"}, "314": {"star_class": "IV", "star_type": "G", "star_subtype": 3, "baseMass": 1.36, "baseTemp": 5760, "diameter": 3.6, "star_colour": "Yellow"}, "315": {"star_class": "IV", "star_type": "G", "star_subtype": 4, "baseMass": 1.28, "baseTemp": 5680, "diameter": 3.8, "star_colour": "Yellow"}, "316": {"star_class": "IV", "star_type": "G", "star_subtype": 5, "baseMass": 1.2, "baseTemp": 5600, "diameter": 4.0, "star_colour": "Yellow"}, "317": {"star_class": "IV", "star_type": "G", "star_subtype": 6, "baseMass": 1.26, "baseTemp": 5520, "diameter": 4.4, "star_colour": "Yellow"}, "318": {"star_class": "IV", "star_type": "G", "star_subtype": 7, "baseMass": 1.32, "baseTemp": 5440, "diameter": 4.8, "star_colour": "Yellow"}, "319": {"star_class": "IV", "star_type": "G", "star_subtype": 8, "baseMass": 1.38, "baseTemp": 5360, "diameter": 5.2, "star_colour": "Yellow"}, "320": {"star_class": "IV", "star_type": "G", "star_subtype": 9, "baseMass": 1.44, "baseTemp": 5280, "diameter": 5.6, "star_colour": "Yellow"}, "321": {"star_class": "IV", "star_type": "K", "star_subtype": 0, "baseMass": 1.5, "baseTemp": 5200, "diameter": 6.0, "star_colour": "Light Orange"}, "322": {"star_class": "IV", "star_type": "K", "star_subtype": 1, "baseMass": 1.56, "baseTemp": 5040, "diameter": 3.8, "star_colour": "Light Orange"}, "323": {"star_class": "IV", "star_type": "K", "star_subtype": 2, "baseMass": 1.62, "baseTemp": 4880, "diameter": 3.6, "star_colour": "Light Orange"}, "324": {"star_class": "IV", "star_type": "K", "star_subtype": 3, "baseMass": 1.68, "baseTemp": 4720, "diameter": 3.4, "star_colour": "Light Orange"}, "325": {"star_class": "IV", "star_type": "K", "star_subtype": 4, "baseMass": 1.74, "baseTemp": 4560, "diameter": 3.2, "star_colour": "Light Orange"}, "326": {"star_class": "V", "star_type": "O", "star_subtype": 0, "baseMass": 90.0, "baseTemp": 50000, "diameter": 20.0, "star_colour": "Blue"}, "327": {"star_class": "V", "star_type": "O", "star_subtype": 1, "baseMass": 84.0, "baseTemp": 48000, "diameter": 18.4, "star_colour": "Blue"}, "328": {"star_class": "V", "star_type": "O", "star_subtype": 2, "baseMass": 78.0, "baseTemp": 46000, "diameter": 16.8, "star_colour": "Blue"}, "329": {"star_class": "V", "star_type": "O", "star_subtype": 3, "baseMass": 72.0, "baseTemp": 44000, "diameter": 15.2, "star_colour": "Blue"}, "330": {"star_class": "V", "star_type": "O", "star_subtype": 4, "baseMass": 66.0, "baseTemp": 42000, "diameter": 13.6, "star_colour": "Blue"}, "331": {"star_class": "V", "star_type": "O", "star_subtype": 5, "baseMass": 60.0, "baseTemp": 40000, "diameter": 12.0, "star_colour": "Blue"}, "332": {"star_class": "V", "star_type": "O", "star_subtype": 6, "baseMass": 51.6, "baseTemp": 38000, "diameter": 3.24, "star_colour": "Blue"}, "333": {"star_class": "V", "star_type": "O", "star_subtype": 7, "baseMass": 43.2, "baseTemp": 36000, "diameter": 2.98, "star_colour": "Blue"}, "334": {"star_class": "V", "star_type": "O", "star_subtype": 8, "baseMass": 34.8, "baseTemp": 34000, "diameter": 2.72, "star_colour": "Blue"}, "335": {"star_class": "V", "star_type": "O", "star_subtype": 9, "baseMass": 25.4, "baseTemp": 32000, "diameter": 2.46, "star_colour": "Blue"}, "336": {"star_class": "V", "star_type": "B", "star_subtype": 0, "baseMass": 18.0, "baseTemp": 30000, "diameter": 7.0, "star_colour": "Blue-White"}, "337": {"star_class": "V", "star_type": "B", "star_subtype": 1, "baseMass": 15.4, "baseTemp": 27000, "diameter": 6.3, "star_colour": "Blue-White"}, "338": {"star_class": "V", "star_type": "B", "star_subtype": 2, "baseMass": 12.8, "baseTemp": 24000, "diameter": 5.6, "star_colour": "Blue-White"}, "339": {"star_class": "V", "star_type": "B", "star_subtype": 3, "baseMass": 10.2, "baseTemp": 21000, "diameter": 4.9, "star_colour": "Blue-White"}, "340": {"star_class": "V", "star_type": "B", "star_subtype": 4, "baseMass": 7.6, "baseTemp": 18000, "diameter": 4.2, "star_colour": "Blue-White"}, "341": {"star_class": "V", "star_type": "B", "star_subtype": 5, "baseMass": 5.0, "baseTemp": 15000, "diameter": 3.5, "star_colour": "Blue-White"}, "342": {"star_class": "V", "star_type": "B", "star_subtype": 6, "baseMass": 4.44, "baseTemp": 14000, "diameter": 3.24, "star_colour": "Blue-White"}, "343": {"star_class": "V", "star_type": "B", "star_subtype": 7, "baseMass": 3.88, "baseTemp": 13000, "diameter": 2.98, "star_colour": "Blue-White"}, "344": {"star_class": "V", "star_type": "B", "star_subtype": 8, "baseMass": 3.32, "baseTemp": 12000, "diameter": 2.72, "star_colour": "Blue-White"}, "345": {"star_class": "V", "star_type": "B", "star_subtype": 9, "baseMass": 2.76, "baseTemp": 11000, "diameter": 2.46, "star_colour": "Blue-White"}, "346": {"star_class": "V", "star_type": "A", "star_subtype": 0, "baseMass": 2.2, "baseTemp": 10000, "diameter": 2.2, "star_colour": "White"}, "347": {"star_class": "V", "star_type": "A", "star_subtype": 1, "baseMass": 2.12, "baseTemp": 9600, "diameter": 2.16, "star_colour": "White"}, "348": {"star_class": "V", "star_type": "A", "star_subtype": 2, "baseMass": 2.04, "baseTemp": 9200, "diameter": 2.12, "star_colour": "White"}, "349": {"star_class": "V", "star_type": "A", "star_subtype": 3, "baseMass": 1.98, "baseTemp": 8800, "diameter": 2.08, "star_colour": "White"}, "350": {"star_class": "V", "star_type": "A", "star_subtype": 4, "baseMass": 1.88, "baseTemp": 8400, "diameter": 2.04, "star_colour": "White"}, "351": {"star_class": "V", "star_type": "A", "star_subtype": 5, "baseMass": 1.8, "baseTemp": 8000, "diameter": 2.0, "star_colour": "White"}, "352": {"star_class": "V", "star_type": "A", "star_subtype": 6, "baseMass": 1.74, "baseTemp": 7600, "diameter": 2.1, "star_colour": "White"}, "353": {"star_class": "V", "star_type": "A", "star_subtype": 7, "baseMass": 1.68, "baseTemp": 7200, "diameter": 2.0, "star_colour": "White"}, "354": {"star_class": "V", "star_type": "A", "star_subtype": 8, "baseMass": 1.62, "baseTemp": 6800, "diameter": 1.9, "star_colour": "White"}, "355": {"star_class": "V", "star_type": "A", "star_subtype": 9, "baseMass": 1.56, "baseTemp": 6400, "diameter": 1.8, "star_colour": "White"}, "356": {"star_class": "V", "star_type": "F", "star_subtype": 0, "baseMass": 1.5, "baseTemp": 7500, "diameter": 1.7, "star_colour": "Yellow-White"}, "357": {"star_class": "V", "star_type": "F", "star_subtype": 1, "baseMass": 1.46, "baseTemp": 7300, "diameter": 1.66, "star_colour": "Yellow-White"}, "358": {"star_class": "V", "star_type": "F", "star_subtype": 2, "baseMass": 1.42, "baseTemp": 7100, "diameter": 1.62, "star_colour": "Yellow-White"}, "359": {"star_class": "V", "star_type": "F", "star_subtype": 3, "baseMass": 1.38, "baseTemp": 6900, "diameter": 1.58, "star_colour": "Yellow-White"}, "360": {"star_class": "V", "star_type": "F", "star_subtype": 4, "baseMass": 1.34, "baseTemp": 6700, "diameter": 1.54, "star_colour": "Yellow-White"}, "361": {"star_class": "V", "star_type": "F", "star_subtype": 5, "baseMass": 1.3, "baseTemp": 6500, "diameter": 1.5, "star_colour": "Yellow-White"}, "362": {"star_class": "V", "star_type": "F", "star_subtype": 6, "baseMass": 1.26, "baseTemp": 6400, "diameter": 1.42, "star_colour": "Yellow-White"}, "363": {"star_class": "V", "star_type": "F", "star_subtype": 7, "baseMass": 1.22, "baseTemp": 6300, "diameter": 1.34, "star_colour": "Yellow-White"}, "364": {"star_class": "V", "star_type": "F", "star_subtype": 8, "baseMass": 1.18, "baseTemp": 6200, "diameter": 1.26, "star_colour": "Yellow-White"}, "365": {"star_class": "V", "star_type": "F", "star_subtype": 9, "baseMass": 1.14, "baseTemp": 6100, "diameter": 1.18, "star_colour": "Yellow-White"}, "366": {"star_class": "V", "star_type": "G", "star_subtype": 0, "baseMass": 1.1, "baseTemp": 6000, "diameter": 1.1, "star_colour": "Yellow"}, "367": {"star_class": "V", "star_type": "G", "star_subtype": 1, "baseMass": 1.06, "baseTemp": 5920, "diameter": 1.07, "star_colour": "Yellow"}, "368": {"star_class": "V", "star_type": "G", "star_subtype": 2, "baseMass": 1.02, "baseTemp": 5840, "diameter": 1.04, "star_colour": "Yellow"}, "369": {"star_class": "V", "star_type": "G", "star_subtype": 3, "baseMass": 0.98, "baseTemp": 5760, "diameter": 1.01, "star_colour": "Yellow"}, "370": {"star_class": "V", "star_type": "G", "star_subtype": 4, "baseMass": 0.94, "baseTemp": 5680, "diameter": 0.98, "star_colour": "Yellow"}, "371": {"star_class": "V", "star_type": "G", "star_subtype": 5, "baseMass": 0.9, "baseTemp": 5600, "diameter": 0.95, "star_colour": "Yellow"}, "372": {"star_class": "V", "star_type": "G", "star_subtype": 6, "baseMass": 0.88, "baseTemp": 5520, "diameter": 0.94, "star_colour": "Yellow"}, "373": {"star_class": "V", "star_type": "G", "star_subtype": 7, "baseMass": 0.86, "baseTemp": 5440, "diameter": 0.93, "star_colour": "Yellow"}, "374": {"star_class": "V", "star_type": "G", "star_subtype": 8, "baseMass": 0.84, "baseTemp": 5360, "diameter": 0.92, "star_colour": "Yellow"}, "375": {"star_class": "V", "star_type": "G", "star_subtype": 9, "baseMass": 0.82, "baseTemp": 5280, "diameter": 0.91, "star_colour": "Yellow"}, "376": {"star_class": "V", "star_type": "K", "star_subtype": 0, "baseMass": 0.8, "baseTemp": 5200, "diameter": 0.9, "star_colour": "Light Orange"}, "377": {"star_class": "V", "star_type": "K", "star_subtype": 1, "baseMass": 0.78, "baseTemp": 5040, "diameter": 0.88, "star_colour": "Light Orange"}, "378": {"star_class": "V", "star_type": "K", "star_subtype": 2, "baseMass": 0.76, "baseTemp": 4880, "diameter": 0.86, "star_colour": "Light Orange"}, "379": {"star_class": "V", "star_type": "K", "star_subtype": 3, "baseMass": 0.74, "baseTemp": 4720, "diameter": 0.84, "star_colour": "Light Orange"}, "380": {"star_class": "V", "star_type": "K", "star_subtype": 4, "baseMass": 0.73, "baseTemp": 4560, "diameter": 0.82, "star_colour": "Light Orange"}, "381": {"star_class": "V", "star_type": "K", "star_subtype": 5, "baseMass": 0.7, "baseTemp": 4400, "diameter": 0.8, "star_colour": "Light Orange"}, "382": {"star_class": "V", "star_type": "K", "star_subtype": 6, "baseMass": 0.66, "baseTemp": 4260, "diameter": 0.78, "star_colour": "Light Orange"}, "383": {"star_class": "V", "star_type": "K", "star_subtype": 7, "baseMass": 0.62, "baseTemp": 4120, "diameter": 0.76, "star_colour": "Light Orange"}, "384": {"star_class": "V", "star_type": "K", "star_subtype": 8, "baseMass": 0.58, "baseTemp": 3980, "diameter": 0.74, "star_colour": "Light Orange"}, "385": {"star_class": "V", "star_type": "K", "star_subtype": 9, "baseMass": 0.54, "baseTemp": 3840, "diameter": 0.72, "star_colour": "Light Orange"}, "386": {"star_class": "V", "star_type": "M", "star_subtype": 0, "baseMass": 0.5, "baseTemp": 3700, "diameter": 0.7, "star_colour": "Orange-Red"}, "387": {"star_class": "V", "star_type": "M", "star_subtype": 1, "baseMass": 0.43, "baseTemp": 3560, "diameter": 0.6, "star_colour": "Orange-Red"}, "388": {"star_class": "V", "star_type": "M", "star_subtype": 2, "baseMass": 0.37, "baseTemp": 3420, "diameter": 0.5, "star_colour": "Orange-Red"}, "389": {"star_class": "V", "star_type": "M", "star_subtype": 3, "baseMass": 0.3, "baseTemp": 3280, "diameter": 0.4, "star_colour": "Orange-Red"}, "390": {"star_class": "V", "star_type": "M", "star_subtype": 4, "baseMass": 0.23, "baseTemp": 3140, "diameter": 0.3, "star_colour": "Orange-Red"}, "391": {"star_class": "V", "star_type": "M", "star_subtype": 5, "baseMass": 0.16, "baseTemp": 3000, "diameter": 0.2, "star_colour": "Orange-Red"}, "392": {"star_class": "V", "star_type": "M", "star_subtype": 6, "baseMass": 0.14, "baseTemp": 2850, "diameter": 0.18, "star_colour": "Orange-Red"}, "393": {"star_class": "V", "star_type": "M", "star_subtype": 7, "baseMass": 0.12, "baseTemp": 2700, "diameter": 0.15, "star_colour": "Orange-Red"}, "394": {"star_class": "V", "star_type": "M", "star_subtype": 8, "baseMass": 0.1, "baseTemp": 2550, "diameter": 0.12, "star_colour": "Orange-Red"}, "395": {"star_class": "V", "star_type": "M", "star_subtype": 9, "baseMass": 0.08, "baseTemp": 2400, "diameter": 0.1, "star_colour": "Orange-Red"}, "396": {"star_class": "VI", "star_type": "O", "star_subtype": 0, "baseMass": 2.0, "baseTemp": 50000, "diameter": 0.18, "star_colour": "Blue"}, "397": {"star_class": "VI", "star_type": "O", "star_subtype": 1, "baseMass": 1.9, "baseTemp": 48000, "diameter": 0.18, "star_colour": "Blue"}, "398": {"star_class": "VI", "star_type": "O", "star_subtype": 2, "baseMass": 1.8, "baseTemp": 46000, "diameter": 0.18, "star_colour": "Blue"}, "399": {"star_class": "VI", "star_type": "O", "star_subtype": 3, "baseMass": 1.7, "baseTemp": 44000, "diameter": 0.18, "star_colour": "Blue"}, "400": {"star_class": "VI", "star_type": "O", "star_subtype": 4, "baseMass": 1.6, "baseTemp": 42000, "diameter": 0.18, "star_colour": "Blue"}, "401": {"star_class": "VI", "star_type": "O", "star_subtype": 5, "baseMass": 1.5, "baseTemp": 40000, "diameter": 0.18, "star_colour": "Blue"}, "402": {"star_class": "VI", "star_type": "O", "star_subtype": 6, "baseMass": 1.3, "baseTemp": 38000, "diameter": 0.18, "star_colour": "Blue"}, "403": {"star_class": "VI", "star_type": "O", "star_subtype": 7, "baseMass": 1.1, "baseTemp": 36000, "diameter": 0.19, "star_colour": "Blue"}, "404": {"star_class": "VI", "star_type": "O", "star_subtype": 8, "baseMass": 0.9, "baseTemp": 34000, "diameter": 0.19, "star_colour": "Blue"}, "405": {"star_class": "VI", "star_type": "O", "star_subtype": 9, "baseMass": 0.7, "baseTemp": 32000, "diameter": 0.19, "star_colour": "Blue"}, "406": {"star_class": "VI", "star_type": "B", "star_subtype": 0, "baseMass": 0.5, "baseTemp": 30000, "diameter": 0.2, "star_colour": "Blue-White"}, "407": {"star_class": "VI", "star_type": "B", "star_subtype": 1, "baseMass": 0.48, "baseTemp": 27000, "diameter": 0.26, "star_colour": "Blue-White"}, "408": {"star_class": "VI", "star_type": "B", "star_subtype": 2, "baseMass": 0.46, "baseTemp": 24000, "diameter": 0.32, "star_colour": "Blue-White"}, "409": {"star_class": "VI", "star_type": "B", "star_subtype": 3, "baseMass": 0.44, "baseTemp": 21000, "diameter": 0.38, "star_colour": "Blue-White"}, "410": {"star_class": "VI", "star_type": "B", "star_subtype": 4, "baseMass": 0.42, "baseTemp": 18000, "diameter": 0.44, "star_colour": "Blue-White"}, "411": {"star_class": "VI", "star_type": "B", "star_subtype": 5, "baseMass": 0.4, "baseTemp": 15000, "diameter": 0.5, "star_colour": "Blue-White"}, "412": {"star_class": "VI", "star_type": "B", "star_subtype": 6, "baseMass": 0.38, "baseTemp": 14000, "diameter": 0.56, "star_colour": "Blue-White"}, "413": {"star_class": "VI", "star_type": "B", "star_subtype": 7, "baseMass": 0.36, "baseTemp": 13000, "diameter": 0.62, "star_colour": "Blue-White"}, "414": {"star_class": "VI", "star_type": "B", "star_subtype": 8, "baseMass": 0.34, "baseTemp": 12000, "diameter": 0.68, "star_colour": "Blue-White"}, "415": {"star_class": "VI", "star_type": "B", "star_subtype": 9, "baseMass": 0.32, "baseTemp": 11000, "diameter": 0.74, "star_colour": "Blue-White"}, "416": {"star_class": "VI", "star_type": "G", "star_subtype": 0, "baseMass": 0.8, "baseTemp": 6000, "diameter": 0.8, "star_colour": "Yellow"}, "417": {"star_class": "VI", "star_type": "G", "star_subtype": 1, "baseMass": 0.78, "baseTemp": 5920, "diameter": 0.78, "star_colour": "Yellow"}, "418": {"star_class": "VI", "star_type": "G", "star_subtype": 2, "baseMass": 0.76, "baseTemp": 5840, "diameter": 0.76, "star_colour": "Yellow"}, "419": {"star_class": "VI", "star_type": "G", "star_subtype": 3, "baseMass": 0.74, "baseTemp": 5760, "diameter": 0.74, "star_colour": "Yellow"}, "420": {"star_class": "VI", "star_type": "G", "star_subtype": 4, "baseMass": 0.72, "baseTemp": 5680, "diameter": 0.72, "star_colour": "Yellow"}, "421": {"star_class": "VI", "star_type": "G", "star_subtype": 5, "baseMass": 0.7, "baseTemp": 5600, "diameter": 0.7, "star_colour": "Yellow"}, "422": {"star_class": "VI", "star_type": "G", "star_subtype": 6, "baseMass": 0.68, "baseTemp": 5520, "diameter": 0.68, "star_colour": "Yellow"}, "423": {"star_class": "VI", "star_type": "G", "star_subtype": 7, "baseMass": 0.66, "baseTemp": 5440, "diameter": 0.66, "star_colour": "Yellow"}, "424": {"star_class": "VI", "star_type": "G", "star_subtype": 8, "baseMass": 0.64, "baseTemp": 5360, "diameter": 0.64, "star_colour": "Yellow"}, "425": {"star_class": "VI", "star_type": "G", "star_subtype": 9, "baseMass": 0.62, "baseTemp": 5280, "diameter": 0.62, "star_colour": "Yellow"}, "426": {"star_class": "VI", "star_type": "K", "star_subtype": 0, "baseMass": 0.6, "baseTemp": 5200, "diameter": 0.6, "star_colour": "Light Orange"}, "427": {"star_class": "VI", "star_type": "K", "star_subtype": 1, "baseMass": 0.58, "baseTemp": 5040, "diameter": 0.56, "star_colour": "Light Orange"}, "428": {"star_class": "VI", "star_type": "K", "star_subtype": 2, "baseMass": 0.56, "baseTemp": 4880, "diameter": 0.56, "star_colour": "Light Orange"}, "429": {"star_class": "VI", "star_type": "K", "star_subtype": 3, "baseMass": 0.54, "baseTemp": 4720, "diameter": 0.54, "star_colour": "Light Orange"}, "430": {"star_class": "VI", "star_type": "K", "star_subtype": 4, "baseMass": 0.52, "baseTemp": 4560, "diameter": 0.52, "star_colour": "Light Orange"}, "431": {"star_class": "VI", "star_type": "K", "star_subtype": 5, "baseMass": 0.5, "baseTemp": 4400, "diameter": 0.5, "star_colour": "Light Orange"}, "432": {"star_class": "VI", "star_type": "K", "star_subtype": 6, "baseMass": 0.48, "baseTemp": 4260, "diameter": 0.48, "star_colour": "Light Orange"}, "433": {"star_class": "VI", "star_type": "K", "star_subtype": 7, "baseMass": 0.46, "baseTemp": 4120, "diameter": 0.46, "star_colour": "Light Orange"}, "434": {"star_class": "VI", "star_type": "K", "star_subtype": 8, "baseMass": 0.44, "baseTemp": 3980, "diameter": 0.44, "star_colour": "Light Orange"}, "435": {"star_class": "VI", "star_type": "K", "star_subtype": 9, "baseMass": 0.42, "baseTemp": 3840, "diameter": 0.42, "star_colour": "Light Orange"}, "436": {"star_class": "VI", "star_type": "M", "star_subtype": 0, "baseMass": 0.5, "baseTemp": 3700, "diameter": 0.4, "star_colour": "Orange-Red"}, "437": {"star_class": "VI", "star_type": "M", "star_subtype": 1, "baseMass": 0.43, "baseTemp": 3560, "diameter": 0.344, "star_colour": "Orange-Red"}, "438": {"star_class": "VI", "star_type": "M", "star_subtype": 2, "baseMass": 0.37, "baseTemp": 3420, "diameter": 0.288, "star_colour": "Orange-Red"}, "439": {"star_class": "VI", "star_type": "M", "star_subtype": 3, "baseMass": 0.3, "baseTemp": 3280, "diameter": 0.232, "star_colour": "Orange-Red"}, "440": {"star_class": "VI", "star_type": "M", "star_subtype": 4, "baseMass": 0.23, "baseTemp": 3140, "diameter": 0.176, "star_colour": "Orange-Red"}, "441": {"star_class": "VI", "star_type": "M", "star_subtype": 5, "baseMass": 0.16, "baseTemp": 3000, "diameter": 0.12, "star_colour": "Orange-Red"}, "442": {"star_class": "VI", "star_type": "M", "star_subtype": 6, "baseMass": 0.14, "baseTemp": 2850, "diameter": 0.109, "star_colour": "Orange-Red"}, "443": {"star_class": "VI", "star_type": "M", "star_subtype": 7, "baseMass": 0.12, "baseTemp": 2700, "diameter": 0.098, "star_colour": "Orange-Red"}, "444": {"star_class": "VI", "star_type": "M", "star_subtype": 8, "baseMass": 0.1, "baseTemp": 2550, "diameter": 0.086, "star_colour": "Orange-Red"}, "445": {"star_class": "VI", "star_type": "M", "star_subtype": 9, "baseMass": 0.08, "baseTemp": 2400, "diameter": 0.075, "star_colour": "Orange-Red"}}}